ca_certificates/__init__.py
gna_resources-0.0.0.dist-info/METADATA
gna_resources-0.0.0.dist-info/WHEEL
gna_resources-0.0.0.dist-info/top_level.txt
gna_resources-0.0.0.dist-info/RECORD
