Metadata-Version: 2.4
Name: gna_resources
Version: 0.0.0
Summary: Dummy gna_resources package for PyPI
Author-email: Your Name <you@example.com>
Requires-Python: >=3.7
